{"46": {"TX_GABARITO": "D", "CO_HABILIDADE": 8, "NU_PARAM_A": 3.66834, "NU_PARAM_B": 1.51081, "NU_PARAM_C": 0.20334, "CO_ITEM": 48333}, "47": {"TX_GABARITO": "E", "CO_HABILIDADE": 13, "NU_PARAM_A": 2.873, "NU_PARAM_B": 1.797, "NU_PARAM_C": 0.217, "CO_ITEM": 7593}, "48": {"TX_GABARITO": "B", "CO_HABILIDADE": 19, "NU_PARAM_A": 1.1637, "NU_PARAM_B": 2.18194, "NU_PARAM_C": 0.20972, "CO_ITEM": 25659}, "49": {"TX_GABARITO": "E", "CO_HABILIDADE": 1, "NU_PARAM_A": 1.5697, "NU_PARAM_B": 0.20392, "NU_PARAM_C": 0.20321, "CO_ITEM": 66857}, "50": {"TX_GABARITO": "E", "CO_HABILIDADE": 4, "NU_PARAM_A": 1.97315, "NU_PARAM_B": 2.44415, "NU_PARAM_C": 0.24037, "CO_ITEM": 23078}, "51": {"TX_GABARITO": "D", "CO_HABILIDADE": 17, "NU_PARAM_A": 2.08163, "NU_PARAM_B": 0.64358, "NU_PARAM_C": 0.17293, "CO_ITEM": 35663}, "52": {"TX_GABARITO": "D", "CO_HABILIDADE": 29, "NU_PARAM_A": 2.24167, "NU_PARAM_B": 0.14792, "NU_PARAM_C": 0.19146, "CO_ITEM": 26554}, "53": {"TX_GABARITO": "E", "CO_HABILIDADE": 6, "NU_PARAM_A": 1.70251, "NU_PARAM_B": 2.02055, "NU_PARAM_C": 0.22855, "CO_ITEM": 29964}, "54": {"TX_GABARITO": "B", "CO_HABILIDADE": 5, "NU_PARAM_A": 1.82448, "NU_PARAM_B": 1.1799, "NU_PARAM_C": 0.20175, "CO_ITEM": 64129}, "55": {"TX_GABARITO": "B", "CO_HABILIDADE": 24, "NU_PARAM_A": 2.35073, "NU_PARAM_B": 0.98505, "NU_PARAM_C": 0.17424, "CO_ITEM": 25144}, "56": {"TX_GABARITO": "B", "CO_HABILIDADE": 12, "NU_PARAM_A": 1.27117, "NU_PARAM_B": 2.38961, "NU_PARAM_C": 0.23535, "CO_ITEM": 8697}, "57": {"TX_GABARITO": "B", "CO_HABILIDADE": 5, "NU_PARAM_A": 2.01946, "NU_PARAM_B": 1.15735, "NU_PARAM_C": 0.22863, "CO_ITEM": 63940}, "58": {"TX_GABARITO": "A", "CO_HABILIDADE": 27, "NU_PARAM_A": 2.9075, "NU_PARAM_B": 0.61307, "NU_PARAM_C": 0.1823, "CO_ITEM": 52841}, "59": {"TX_GABARITO": "B", "CO_HABILIDADE": 25, "NU_PARAM_A": 3.25992, "NU_PARAM_B": 0.55233, "NU_PARAM_C": 0.27105, "CO_ITEM": 37869}, "60": {"TX_GABARITO": "A", "CO_HABILIDADE": 15, "NU_PARAM_A": 1.73192, "NU_PARAM_B": 1.39706, "NU_PARAM_C": 0.24778, "CO_ITEM": 30260}, "61": {"TX_GABARITO": "D", "CO_HABILIDADE": 22, "NU_PARAM_A": 1.26659, "NU_PARAM_B": 2.0806, "NU_PARAM_C": 0.25037, "CO_ITEM": 63671}, "62": {"TX_GABARITO": "E", "CO_HABILIDADE": 22, "NU_PARAM_A": 1.88229, "NU_PARAM_B": 1.99194, "NU_PARAM_C": 0.24511, "CO_ITEM": 49493}, "63": {"TX_GABARITO": "D", "CO_HABILIDADE": 3, "NU_PARAM_A": 1.54269, "NU_PARAM_B": 1.65171, "NU_PARAM_C": 0.23976, "CO_ITEM": 47937}, "64": {"TX_GABARITO": "C", "CO_HABILIDADE": 7, "NU_PARAM_A": 2.05773, "NU_PARAM_B": 1.1812, "NU_PARAM_C": 0.20371, "CO_ITEM": 63689}, "65": {"TX_GABARITO": "B", "CO_HABILIDADE": 6, "NU_PARAM_A": 1.95719, "NU_PARAM_B": 2.01242, "NU_PARAM_C": 0.17502, "CO_ITEM": 34536}, "66": {"TX_GABARITO": "E", "CO_HABILIDADE": 20, "NU_PARAM_A": 2.77907, "NU_PARAM_B": 0.63855, "NU_PARAM_C": 0.21535, "CO_ITEM": 39273}, "67": {"TX_GABARITO": "C", "CO_HABILIDADE": 1, "NU_PARAM_A": 2.0462, "NU_PARAM_B": 2.54165, "NU_PARAM_C": 0.29431, "CO_ITEM": 9357}, "68": {"TX_GABARITO": "A", "CO_HABILIDADE": 28, "NU_PARAM_A": 4.06054, "NU_PARAM_B": 1.33205, "NU_PARAM_C": 0.15121, "CO_ITEM": 40684}, "69": {"TX_GABARITO": "B", "CO_HABILIDADE": 15, "NU_PARAM_A": 2.13865, "NU_PARAM_B": 1.66066, "NU_PARAM_C": 0.16643, "CO_ITEM": 60687}, "70": {"TX_GABARITO": "D", "CO_HABILIDADE": 2, "NU_PARAM_A": 1.85369, "NU_PARAM_B": 1.36339, "NU_PARAM_C": 0.17458, "CO_ITEM": 41694}, "71": {"TX_GABARITO": "D", "CO_HABILIDADE": 9, "NU_PARAM_A": 1.84758, "NU_PARAM_B": 0.90973, "NU_PARAM_C": 0.20024, "CO_ITEM": 31131}, "72": {"TX_GABARITO": "E", "CO_HABILIDADE": 16, "NU_PARAM_A": 2.73576, "NU_PARAM_B": 0.16142, "NU_PARAM_C": 0.18803, "CO_ITEM": 60452}, "73": {"TX_GABARITO": "E", "CO_HABILIDADE": 8, "NU_PARAM_A": 2.35337, "NU_PARAM_B": 2.80892, "NU_PARAM_C": 0.26609, "CO_ITEM": 68280}, "74": {"TX_GABARITO": "E", "CO_HABILIDADE": 30, "NU_PARAM_A": 2.117, "NU_PARAM_B": 1.32282, "NU_PARAM_C": 0.16142, "CO_ITEM": 30973}, "75": {"TX_GABARITO": "A", "CO_HABILIDADE": 23, "NU_PARAM_A": 2.2379, "NU_PARAM_B": 0.3846, "NU_PARAM_C": 0.195, "CO_ITEM": 49082}, "76": {"TX_GABARITO": "A", "CO_HABILIDADE": 14, "NU_PARAM_A": 2.71723, "NU_PARAM_B": 2.25622, "NU_PARAM_C": 0.08474, "CO_ITEM": 25415}, "77": {"TX_GABARITO": "B", "CO_HABILIDADE": 10, "NU_PARAM_A": 2.53387, "NU_PARAM_B": 1.32886, "NU_PARAM_C": 0.19106, "CO_ITEM": 27543}, "78": {"TX_GABARITO": "B", "CO_HABILIDADE": 11, "NU_PARAM_A": 3.16238, "NU_PARAM_B": 0.72343, "NU_PARAM_C": 0.17767, "CO_ITEM": 40015}, "79": {"TX_GABARITO": "C", "CO_HABILIDADE": 3, "NU_PARAM_A": 1.87006, "NU_PARAM_B": 1.01072, "NU_PARAM_C": 0.22396, "CO_ITEM": 38137}, "80": {"TX_GABARITO": "C", "CO_HABILIDADE": 18, "NU_PARAM_A": 2.53646, "NU_PARAM_B": 1.90178, "NU_PARAM_C": 0.13566, "CO_ITEM": 26637}, "81": {"TX_GABARITO": "B", "CO_HABILIDADE": 24, "NU_PARAM_A": 2.06671, "NU_PARAM_B": 1.41792, "NU_PARAM_C": 0.11486, "CO_ITEM": 54721}, "82": {"TX_GABARITO": "C", "CO_HABILIDADE": 7, "NU_PARAM_A": 2.9944, "NU_PARAM_B": 0.82283, "NU_PARAM_C": 0.18535, "CO_ITEM": 63636}, "83": {"TX_GABARITO": "A", "CO_HABILIDADE": 23, "NU_PARAM_A": 1.52723, "NU_PARAM_B": 0.90605, "NU_PARAM_C": 0.19032, "CO_ITEM": 13714}, "84": {"TX_GABARITO": "B", "CO_HABILIDADE": 5, "NU_PARAM_A": 2.10071, "NU_PARAM_B": 0.37934, "NU_PARAM_C": 0.20127, "CO_ITEM": 47522}, "85": {"TX_GABARITO": "D", "CO_HABILIDADE": 26, "NU_PARAM_A": 2.10216, "NU_PARAM_B": 0.54058, "NU_PARAM_C": 0.20367, "CO_ITEM": 49003}, "86": {"TX_GABARITO": "D", "CO_HABILIDADE": 21, "NU_PARAM_A": 2.68863, "NU_PARAM_B": 1.57887, "NU_PARAM_C": 0.1554, "CO_ITEM": 7963}, "87": {"TX_GABARITO": "A", "CO_HABILIDADE": 11, "NU_PARAM_A": 1.94431, "NU_PARAM_B": 1.07648, "NU_PARAM_C": 0.17055, "CO_ITEM": 64128}, "88": {"TX_GABARITO": "E", "CO_HABILIDADE": 23, "NU_PARAM_A": 1.89088, "NU_PARAM_B": 0.55265, "NU_PARAM_C": 0.18064, "CO_ITEM": 47826}, "89": {"TX_GABARITO": "E", "CO_HABILIDADE": 3, "NU_PARAM_A": 1.90038, "NU_PARAM_B": 0.95351, "NU_PARAM_C": 0.02785, "CO_ITEM": 63684}, "90": {"TX_GABARITO": "C", "CO_HABILIDADE": 18, "NU_PARAM_A": 3.97573, "NU_PARAM_B": 0.53716, "NU_PARAM_C": 0.18987, "CO_ITEM": 24552}}